KLineAnalys-0.0.1.1.dist-info/METADATA
KLineAnalys-0.0.1.1.dist-info/RECORD
KLineAnalys-0.0.1.1.dist-info/WHEEL
KLineAnalys-0.0.1.1.dist-info/top_level.txt
KLineAnalysis/GetDate.py
KLineAnalysis/KLineFeatures.py
KLineAnalysis/TrendAnalysis.py
KLineAnalysis/__init__.py
