Metadata-Version: 1.0
Name: KLineAnalys
Version: 0.0.1.1
Summary: this is a Finance Analysis System
Home-page: https://github.com/670428704/FinanceAnalysis.git
Author: fdsn
Author-email: 670428704@qq.com
License: UNKNOWN
Platform: UNKNOWN
